pplox/__init__.py
pplox/ast_printer.py
pplox/cli.py
pplox/environment.py
pplox/error_reporter.py
pplox/expr.py
pplox/interpreter.py
pplox/interpreter_error.py
pplox/parser.py
pplox/scanner.py
pplox/stmt.py
pplox/token.py
pplox/token_type.py
pplox-0.0.7.dist-info/METADATA
pplox-0.0.7.dist-info/WHEEL
pplox-0.0.7.dist-info/entry_points.txt
pplox-0.0.7.dist-info/top_level.txt
pplox-0.0.7.dist-info/RECORD
