Metadata-Version: 2.1
Name: pplox
Version: 0.0.7
Summary: Interpreter for the Lox programming language
Author-email: Karl Cagalawan <karl.cagalawan@gmail.com>
Project-URL: Repository, https://www.github.com/karlcaga/pplox
Project-URL: Issues, https://github.com/karlcaga/pplox/issues
Project-URL: Documentation, https://pplox.readthedocs.io/en/latest/
Requires-Python: >=3.12
